[
  {
    "slug": "longest-substring-without-repeating",
    "title": "Takrorlanmaydigan eng uzun substring",
    "difficulty": "MEDIUM",
    "categories": ["string", "hash-table", "sliding-window"],
    "tags": ["algorithms", "string", "hash-table", "sliding-window"],
    "description": "Berilgan stringda takrorlanmaydigan belgilardan iborat eng uzun substringning uzunligini toping.",
    "descriptionHtml": "<p>Berilgan stringda takrorlanmaydigan belgilardan iborat eng uzun substringning uzunligini toping.</p>",
    "examples": [
      {
        "caseNumber": "1",
        "input": "s = \"abcabcbb\"",
        "target": null,
        "output": "3",
        "explanation": "Javob \"abc\" bo'lib, uzunligi 3"
      },
      {
        "caseNumber": "2",
        "input": "s = \"bbbbb\"",
        "target": null,
        "output": "1",
        "explanation": "Javob \"b\" bo'lib, uzunligi 1"
      }
    ],
    "constraints": [
      "0 <= s.length <= 5 * 10^4"
    ],
    "hints": [
      "Sliding window texnikasidan foydalaning",
      "Hash set yoki hash map ishlatishingiz mumkin"
    ],
    "codeTemplates": {
      "java": "class Solution {\n    public int lengthOfLongestSubstring(String s) {\n        \n    }\n}",
      "python": "class Solution:\n    def length_of_longest_substring(self, s: str) -> int:\n        ",
      "javascript": "/**\n * @param {string} s\n * @return {number}\n */\nvar lengthOfLongestSubstring = function(s) {\n    \n};",
      "cpp": "class Solution {\npublic:\n    int lengthOfLongestSubstring(string s) {\n        \n    }\n};"
    },
    "testCases": [
      {
        "input": "\"abcabcbb\"",
        "expectedOutput": "3",
        "isHidden": false,
        "timeLimitMs": 2000
      },
      {
        "input": "\"bbbbb\"",
        "expectedOutput": "1",
        "isHidden": false,
        "timeLimitMs": 2000
      }
    ],
    "relatedProblems": [],
    "companies": ["Amazon", "Google", "Facebook"],
    "frequency": 0.85,
    "isPremium": false
  },
  {
    "slug": "container-with-most-water",
    "title": "Eng ko'p suv sig'adigan konteyner",
    "difficulty": "MEDIUM",
    "categories": ["array", "two-pointers"],
    "tags": ["algorithms", "array", "two-pointers"],
    "description": "Berilgan massivda eng ko'p suv sig'adigan konteyner hajmini toping.",
    "descriptionHtml": "<p>Berilgan massivda eng ko'p suv sig'adigan konteyner hajmini toping.</p>",
    "examples": [
      {
        "caseNumber": "1",
        "input": "height = [1,8,6,2,5,4,8,3,7]",
        "target": null,
        "output": "49",
        "explanation": "Maksimal hajm 49"
      }
    ],
    "constraints": [
      "n >= 2",
      "0 <= height[i] <= 3 * 10^4"
    ],
    "hints": [
      "Two pointers texnikasidan foydalaning",
      "Kichik balandlikdagi pointer'ni harakat ettiring"
    ],
    "codeTemplates": {
      "java": "class Solution {\n    public int maxArea(int[] height) {\n        \n    }\n}",
      "python": "class Solution:\n    def max_area(self, height: List[int]) -> int:\n        ",
      "javascript": "/**\n * @param {number[]} height\n * @return {number}\n */\nvar maxArea = function(height) {\n    \n};",
      "cpp": "class Solution {\npublic:\n    int maxArea(vector<int>& height) {\n        \n    }\n};"
    },
    "testCases": [
      {
        "input": "[1,8,6,2,5,4,8,3,7]",
        "expectedOutput": "49",
        "isHidden": false,
        "timeLimitMs": 2000
      }
    ],
    "relatedProblems": [],
    "companies": ["Microsoft", "Apple"],
    "frequency": 0.80,
    "isPremium": false
  }
]